[
  {
    "content_id": 499115,
    "reference_id": 202738,
    "title": "تسالونيكي الأولى",
    "media_type": "Text",
    "index_reference": "52000000",
    "language": "arb",
    "content": "<p><strong>ما هي رسالة تسالونيكي الأولى؟</strong></p><ul><li><p>رسالة تسالونيكي الأولى هي رسالة من الرسول بولس. وقد ساعده سيلا وتيموثاوس في كتابتها.</p></li><li><p>يُعتقد أن بولس كتب هذه الرسالة من كورنثوس حوالي عام 51 ميلادي.</p></li><li><p>يتضمن العهد الجديد رسالتين من بولس إلى الكنيسة في تسالونيكي. هذه هي الرسالة الأولى.</p></li></ul><p><strong>لمن كُتبت رسالة تسالونيكي الأولى؟</strong></p><ul><li><p>إلى المؤمنين في مدينة تسالونيكي. وقد كان بعضهم يهودًا ولكن معظمهم كانوا من الأمم.</p></li><li><p>تمت قراءة الرسالة بصوت عالٍ في الكنائس في جميع أنحاء منطقة تسالونيكي.</p></li><li><p>يدرك أتباع يسوع أن رسالة تسالونيكي الأولى تشارك الحق عن يسوع. لذلك فهي لجميع الناس في كل مكان.</p></li></ul><p><strong>لماذا كُتبت رسالة تسالونيكي الأولى؟</strong></p><ul><li><p>لمشاركة فرح الرسول بولس بأن أهل تسالونيكي كانوا أمناء ليسوع.</p></li><li><p>لتوضيح عمل بولس بينهم.</p></li><li><p>للإجابة على الأسئلة التي كان قد طرحها المؤمنون في تسالونيكي على بولس. وقد كانت هذه الأسئلة تتعلق بالموت وعودة يسوع إلى الأرض.</p></li></ul><p><strong>الأفكار الرئيسية</strong></p><ul><li><p>بولس يشجع الكنيسة في تسالونيكي.</p></li><li><p>عمل بولس كرسول.</p></li><li><p>تعليمات حول الحياة المُقَدَّسة.</p></li><li><p>رجوع يسوع إلى الأرض.</p></li></ul><p><strong>مخطط السفر</strong></p><p><strong>بولس يشكر الله من أجل إيمان أهل تسالونيكي (1).</strong></p><p><strong>بولس يشرح عمله كرسول في تسالونيكي (2:1 – 3:10).</strong></p><p><strong>بولس يصلي من أجل أهل تسالونيكي (3:11–13).</strong></p><p><strong>بولس يشجع أهل تسالونيكي (4:1 – 5:22).</strong></p><p><strong>التحيات الختامية (5:23–28).</strong></p>",
    "associations": {
      "passage": [
        {
          "start_ref": "52001001",
          "start_ref_usfm": "1TH 1:1",
          "end_ref": "52001001",
          "end_ref_usfm": "1TH 1:1"
        }
      ],
      "resource": []
    }
  }
]