[
  {
    "content_id": 499207,
    "reference_id": 202764,
    "version": "1.0.1",
    "title": "列王紀下",
    "media_type": "Text",
    "index_reference": "12000000",
    "language": "zht",
    "review_level": "None",
    "content": "<p><strong>列王紀下是一卷什麼樣的書？</strong></p><ul><li><p>列王紀下是以色列歷史的記載。這些事件發生在公元前850年至560年間，關於這些事件的故事流傳了數百年，它們在以色列和猶太家庭中代代相傳。</p></li><li><p>一般認為先知耶利米記錄了這些故事的一部分，人們認為這些故事在公元前560年左右寫成。</p></li><li><p>列王紀下的其它部分則由其他的以色列人所記錄下來。</p></li><li><p>列王紀上和列王紀下最初是一卷書，後來被分成兩卷。</p></li></ul><p><strong>這卷書為誰而寫？</strong></p><ul><li><p>寫給以色列的百姓。</p></li></ul><p><strong>列王紀下為何而寫？</strong></p><ul><li><p>為了記錄北國的君王和南國的君王的事蹟。</p></li><li><p>為了說明為什麼北國和南國被毀滅並被擄到外邦。</p></li><li><p>撒母耳記上、撒母耳記下、列王紀上和列王紀下共同構成一個完整的故事，記錄了超過四百年的以色列歷史。</p></li></ul><p><strong>主要思想</strong></p><ul><li><p>先知挑戰那些不忠於神的統治者。</p></li><li><p>大多數北國和南國的君王拒絕單單敬拜和事奉神。</p></li><li><p>神因百姓不遵守西奈山之約而審判他們，祂使用亞述和巴比倫作為審判的工具。</p></li></ul><p><strong>大綱</strong></p><p><strong>北國的君王和南國的君王（1 – 17章）。</strong></p><p><strong>南國（18－25章）。</strong></p>",
    "associations": {
      "passage": [
        {
          "start_ref": "12001001",
          "start_ref_usfm": "2KI 1:1",
          "end_ref": "12001001",
          "end_ref_usfm": "2KI 1:1"
        }
      ],
      "resource": []
    }
  }
]